MANIFEST.in
README.rst
packages.html
pyproject.toml
setup.py
tox.ini
corona_lab/__init__.py
corona_lab/analysis.py
corona_lab/build_corona.py
corona_lab/corona.py
corona_lab/ecm.py
corona_lab/freefree.py
corona_lab/utils.py
corona_lab/version.py
corona_lab.egg-info/PKG-INFO
corona_lab.egg-info/SOURCES.txt
corona_lab.egg-info/dependency_links.txt
corona_lab.egg-info/not-zip-safe
corona_lab.egg-info/requires.txt
corona_lab.egg-info/top_level.txt
corona_lab/data/README.rst
corona_lab/tests/__init__.py
corona_lab/tests/test_analysis.py
corona_lab/tests/test_build_corona.py
corona_lab/tests/test_ecm.py
corona_lab/tests/test_freefree.py
corona_lab/tests/test_model.py
corona_lab/tests/test_utils.py
corona_lab/tests/utils_for_test.py
corona_lab/tests/data/coord_test.ecsv
corona_lab/tests/data/example_cube.ecsv
corona_lab/tests/data/example_dyn_spec.dat
corona_lab/tests/data/example_model.ecsv
corona_lab/tests/data/example_table.ecsv
corona_lab/tests/data/process_fieldlines_ex.ecsv
corona_lab/tests/data/test.img
docs/LICENSE.rst
docs/Makefile
docs/api.rst
docs/conf.py
docs/index.rst
docs/intro.rst
docs/make.bat
docs/requirements.txt
docs/_static/banner.svg
docs/_static/coronalab.css
docs/_static/coronalab.svg
docs/_static/documentation.svg
docs/_static/github.svg
docs/_static/icon.png
docs/_static/installation.svg
docs/_static/license.svg
docs/_static/logos.svg