Metadata-Version: 2.4
Name: corona_lab
Version: 0.1.1
Summary: Tool for created synthetic observations from a model stellar magnetic corona.
Author-email: "C. E. Brasseur" <cb432@st-andrews.ac.uk>
Project-URL: repository, https://github.com/St-andrews-cool-stars/CoronaLab.git
Requires-Python: >=3.8
Requires-Dist: astropy
Requires-Dist: scipy
Requires-Dist: scikit-image
Requires-Dist: sunpy
Requires-Dist: sunkit-magex
Provides-Extra: test
Requires-Dist: pytest; extra == "test"
Requires-Dist: pytest-doctestplus; extra == "test"
Provides-Extra: docs
Requires-Dist: sphinx; extra == "docs"
Requires-Dist: sphinx-automodapi; extra == "docs"
Requires-Dist: tomli; python_version < "3.11" and extra == "docs"
Requires-Dist: pydata-sphinx-theme; extra == "docs"
Requires-Dist: matplotlib; extra == "docs"
